tests/ipynb/__init__.py
tests/ipynb/test_core.py
tests/ipynb/test_fairseq.py
tests/scorers/__init__.py
tests/scorers/test_bert_score.py
tests/scorers/test_bleu.py
tests/scorers/test_bp.py
tests/scorers/test_chrf.py
tests/scorers/test_cider.py
tests/scorers/test_gleu.py
tests/scorers/test_laser.py
tests/scorers/test_meteor.py
tests/scorers/test_nist.py
tests/scorers/test_ribes.py
tests/scorers/test_rouge_1.py
tests/scorers/test_rouge_2.py
tests/scorers/test_rouge_l.py
tests/scorers/test_ter.py
tests/scorers/test_wer.py
tests/scorers/test_wer_del.py
tests/scorers/test_wer_ins.py
tests/scorers/test_wer_sub.py
vizseq/VERSION
vizseq/__init__.py
vizseq/server.py
vizseq/_aligners/__init__.py
vizseq/_aligners/speech_aligner.py
vizseq/_aligners/text_aligner.py
vizseq/_data/__init__.py
vizseq/_data/config_manager.py
vizseq/_data/data_sources.py
vizseq/_data/google_translate.py
vizseq/_data/lang_tagger.py
vizseq/_data/n_grams.py
vizseq/_data/stats.py
vizseq/_data/table_exporter.py
vizseq/_data/tokenizers.py
vizseq/_data/zip_file.py
vizseq/_templates/about.html
vizseq/_templates/base.html
vizseq/_templates/config.html
vizseq/_templates/ipynb_n_grams.html
vizseq/_templates/ipynb_scores.html
vizseq/_templates/ipynb_stats.html
vizseq/_templates/ipynb_view.html
vizseq/_templates/macros.html
vizseq/_templates/tasks.html
vizseq/_templates/upload.html
vizseq/_templates/view.html
vizseq/_utils/__init__.py
vizseq/_utils/json.py
vizseq/_utils/logger.py
vizseq/_utils/optional.py
vizseq/_view/__init__.py
vizseq/_view/data_filter.py
vizseq/_view/data_sorters.py
vizseq/_view/data_view.py
vizseq/_view/mem_cached_data_getters.py
vizseq/_view/num_formatter.py
vizseq/_view/web_view.py
vizseq/_visualizers/__init__.py
vizseq/_visualizers/dict_visualizer.py
vizseq/_visualizers/seq_visualizer.py
vizseq/ipynb/__init__.py
vizseq/ipynb/core.py
vizseq/ipynb/fairseq_viz.py
vizseq/scorers/__init__.py
vizseq/scorers/_ter.py
vizseq/scorers/_wer.py
vizseq/scorers/bert_score.py
vizseq/scorers/bleu.py
vizseq-0.1.15.dist-info/LICENSE
vizseq-0.1.15.dist-info/METADATA
vizseq-0.1.15.dist-info/WHEEL
vizseq-0.1.15.dist-info/top_level.txt
vizseq-0.1.15.dist-info/RECORD
