Metadata-Version: 2.1
Name: vizseq
Version: 0.1.15
Summary: Visual Analysis Toolkit for Text Generation Tasks
Home-page: https://github.com/facebookresearch/vizseq
License: MIT
Platform: UNKNOWN
Classifier: Intended Audience :: Science/Research
Classifier: Programming Language :: Python :: 3.6
Classifier: Programming Language :: Python :: 3.7
Classifier: Programming Language :: Python :: 3.8
Classifier: Programming Language :: Python :: 3 :: Only
Classifier: Topic :: Scientific/Engineering :: Artificial Intelligence
Requires-Dist: numpy
Requires-Dist: sacrebleu (>=1.4.13)
Requires-Dist: torch
Requires-Dist: tqdm
Requires-Dist: nltk (>=3.5)
Requires-Dist: py-rouge
Requires-Dist: langid
Requires-Dist: google-cloud-translate
Requires-Dist: jinja2
Requires-Dist: IPython
Requires-Dist: matplotlib
Requires-Dist: tornado
Requires-Dist: pandas
Requires-Dist: soundfile
Requires-Dist: laserembeddings
Requires-Dist: bert-score
